mcp_wolfram_alpha/__init__.py
mcp_wolfram_alpha/server.py
mcp_wolfram_alpha/wolfram_client.py
mseep_mcp_wolfram_alpha-0.2.3.dist-info/licenses/LICENSE
mseep_mcp_wolfram_alpha-0.2.3.dist-info/METADATA
mseep_mcp_wolfram_alpha-0.2.3.dist-info/WHEEL
mseep_mcp_wolfram_alpha-0.2.3.dist-info/entry_points.txt
mseep_mcp_wolfram_alpha-0.2.3.dist-info/top_level.txt
mseep_mcp_wolfram_alpha-0.2.3.dist-info/RECORD
